[{"date":"2026-06-27","total":53159,"open":44616,"draft":1766,"submit":3426,"reject":443,"approve":2908,"pct":12.75,"korwil":{"Antonius M. Ladjar":12.8,"Gunawan Zulfi, S.Tr.Stat":21.3,"Yustinus Laba, SE":17.3,"M. Aliuddin AP":13.3,"Laila Choirun Nimah, S. Tr. Stat":12.4,"Eduard Manuel Fernandez, S.Tr.Stat":10.3,"Tresia Ose, SE":10.6,"Yakobus Laba Uran":20.5,"Komang Uning Sari Devi, S.Tr.Stat":13.6,"Rusman Fahri, S.Tr.Stat":13.7,"Michael Jonas S, S.Tr.Stat":16.7,"Rusdin Ashari Syarif, SE":15.1,"Zainudin Manur, S.Tr.Stat":10.6,"Maria Kewa, S.Tr.Stat":15.6,"Yanuarius Dudeng, SE":9.5,"Yulianus Ronaldias, S.Tr.Stat":9.9,"Paulus Emilius Riberu":9.7,"Tias Arta Putra, S.Tr.Stat":14.2,"Yasin Hasan":8.5,"Ferdinandus Edi Nedabang":9.7,"Alfiano Petrus Seran Nahak, A.Md.Stat":10.6},"kec":{"ATADEI":16.9,"BUYASARI":14.3,"ILE APE":10.4,"ILE APE TIMUR":20.5,"LEBATUKAN":13.6,"NAGAWUTUNG":15.9,"NUBATUKAN":11.6,"OMESURI":10.7,"WULANDONI":10.2},"pml":{"Lukas Lolik Karang":12.8,"Paulus Samung Sarahutu":21.3,"Yulius Liwuq":17.9,"Muhammad La Aji":13.3,"Vincensius Filu":12,"Sulviyati Mursid":10.3,"Bernardus Parlete Lagamaking":10.6,"Antonius Basi":20.5,"Marianus Duli Lasar":13.6,"Lukas Edison Rimong":13.7,"Katharina Penuru Botoor":16.7,"Suriati Seni":15.1,"Philipus Banin":10.6,"Arnoldus Gesi":15.6,"Maria Herlina":9.5,"Beata Benedikta Siba Sinuor":9.9,"Marselinus Murin":9.7,"Jamrud Arifin":14.2,"Valentina Katarina Lakaq":8.5,"Gabriel Guna Beding":9.7,"Gabriel Gowing Blikololong":10.6},"ppl":{"Andreas Fransiskus Olak":5.8,"Gaspar Mangu":13.8,"Berta Siti Susanti":16.7,"Feliks Tarbala Watun":24.8,"Markus Mado Wutun":25.4,"Christian Alexander Ola Manuk":17.4,"Gregorius Petrus Pito":24.7,"Beatrix Luisa Duan":24.8,"Mikael Fransiskus Sidu":13.8,"Oswaldus Breok Namang":12.7,"Andreas Jongi Rebong":5.5,"Adolfus Ratu":18,"Matheus Matan":13.4,"Isaq Ayub":12.9,"Pius Bala":27.9,"Markus Kewaaman":24.4,"Donatus Nalaq":17.5,"Oktavianus Laba":5.6,"Thomas Tamal":9.4,"Erni Wati":20.8,"Ardi Umar":16.1,"Anastasia Areq":10,"Yosep Dula":12,"Wahidin Kaharudin":12.4,"Agnes Isabela Derang":8.6,"Longginus Moniq":9.3,"Edmundus Waiq":10.5,"Fransiska Peni":14.1,"Marianus Yohanes Rehing":20.6,"Raimundus Pati":18.9,"Maruntu Jumadi":6.5,"Blasius Tuaq":11,"Siti Qomaria Hasan":20.5,"Elias Uta":16.3,"Maria Petronela Date Kothan":9.5,"Damasus Gega":22.3,"Tajudin Angin Bin Abidin":2.3,"Siti Kadaria":6.9,"Apolonarius H. Ekeng":8.3,"Elisabeth Uba":5.6,"Ignasia Novianti Luku":17,"Yohana Uba Ladopurab":12.7,"Aloysius Yulianto Sandro Laba":7.2,"Hendrikus B. Ado Bomaking":13.8,"Damianus Deveuster Lemay":5.7,"Damianus Halan Lelangona":9,"Albertus Masan Ladoangin":6.1,"Abdulrahman Kewaman":21.3,"Paskasius Andreas Dupont":6.5,"Yanuarius Emilson Ola":18.6,"Dismas Palmasius Doni Witak":12.6,"Maria Paskalina Karolina Ina Wae":22.7,"Yohanes Soge":21.8,"Arnoldus Yansen Laot":16,"Leonardus Batista Ero":18.5,"Gebhardus Arispusjoyo Kedang":33.7,"Elfira Deta Tuto":7.1,"Theodorus Rivaldo Nani Lazaren":15.2,"Agustinus Gasa Lengari":11.6,"Yul Fransiska Pulo":11.7,"Mediatriks Valentina S. Kayo":19.2,"Ferentina Martina Unarajan":16.4,"Maria Incensia S.Say":9.3,"Maria Magdalena Runi":12.8,"Maria Vinensia Sura":36.1,"Elisabet Ero":9.4,"Imelda Triputri Neti":8.8,"Fransiskus L. Lelet":17,"Qamaria Suryati Harun":9.3,"Nurhuspita Ina Masa":10.7,"Arnolda Stefania Tuto":21.8,"Marianus Keluli":10.2,"Bonifasius Doni":8.8,"Mustapa Badarudin":20.2,"Berchemans Yohanes Afio Sittu Belitin":13.7,"Andreas Guma":10.7,"Muhamad Sidik":16.5,"Nurlaila Hanun Bengang":16.7,"Theresia Yulianti Botoor":23.7,"Nandamh Syahputra":28.1,"Veronika Wetan Bataona":5.1,"Elisabeth Olainang":9.1,"Ferdinandus Bubun Pegan":16.5,"Sonia Saputri Toebajoe":11.9,"Katarina Kidi":14.2,"Lidwina Putri Kamalera":14.1,"Maria Sovia Deran":8.2,"Rizqi Aulia Fajarwati Hassan":11.4,"Maria Dolorosa Klara Moru Muda":10.5,"Maria Inselma Ina Peni Lagaor":8.4,"Yohakim Saverius Tea":13.2,"Yohanita Anu":11.8,"Archangela Dwi Putri Ikapati Ingulyman":5.7,"Frumensia Ivanna":7.1,"Margareta Mellinia Peni Pureklolon":17.5,"Ilham Samida":9.1,"Imakulata Peni Kedang":2.4,"Indah Sulastri Achmad":18,"Andriani Amelia Merbhy Pala":12.8,"Elisabeth Sose Ika Wulandari Erap":13.7,"Emiliana Leti Lepuan":6.3,"Maria A. K. Nini Belutowe":10.1,"Yosafat Demon Making":12.4,"Hasna Wati Latif":22.8,"Sarianti Manur":23.6,"Siti Sara Binti Gani":18.4,"Siti Jamilah":9.9,"Anastasia Natalia Selaka Dasion":1,"Anita Rutania Malang":13.1,"Donatus Lewo Puho":6,"Paulus Utan Soge Watun":9.3,"Sitti Khodidjah":9.8,"Maria Kristina Lema":13.9,"Anastasia Heba":12.4,"Rovika Rusli Atapukan":15.6,"Samsudin Beyeng":19.8,"Ikrimah Subih":6.1,"Muhammad Sirajudin":26.3,"Angely Vitama Areq":8.8,"Paulus Bapa Edangwala":8.3,"Muhamad Salim Sigran Kamaludin":16,"Fransiska Inang":5.4,"Yustina Sani":6.9,"Yustina Inaq":10.1,"Agustina Areq":7.3,"Suwarti Muhammad":12.6,"Kornelis Kopa":6.9,"Yuvensia Rosmiyanti Leto":9.3,"Bernardus Boli Nedaqwala":10.1,"Bahmit Boli":9.6,"Al Imran Jubair":11.9,"Ignasius Laka Nolowala":14.2,"Valentinus Tien":5.1,"Muhamad Faujun":4.8,"Alberta Tenuli":6,"Abdullah Kahar Rongan":6.5,"Melkhior Ahal":15.4,"Maria Javalepangina Wujon":9,"Oktavianus Gudi Bataona":7.4,"Yosefina Dewi":4.9,"Siti Nurbaya Mayeli":10.2,"Samsul Riyadi":13,"Fransiskus Wati Lanang":14.7,"Paskalis Marto Muli":13.1,"Gabriel Notan Key":13.2}}]